goat_mcp_add_server/__init__.py
goat_mcp_add_server-0.1.0.dist-info/WHEEL
goat_mcp_add_server-0.1.0.dist-info/entry_points.txt
goat_mcp_add_server-0.1.0.dist-info/METADATA
goat_mcp_add_server-0.1.0.dist-info/RECORD
